isodata/__init__.py
isodata/base.py
isodata/caiso.py
isodata/decorators.py
isodata/ercot.py
isodata/isone.py
isodata/miso.py
isodata/nyiso.py
isodata/pjm.py
isodata/spp.py
isodata/test.py
isodata/utils.py
isodata/version.py
isodata/tests/__init__.py
isodata/tests/conftest.py
isodata/tests/test_caiso.py
isodata/tests/test_ercot.py
isodata/tests/test_isos.py
isodata/tests/test_miso.py
isodata/tests/test_nyiso.py
isodata/tests/test_pjm.py
isodata/tests/test_version.py
isodata-0.10.0.dist-info/LICENSE
isodata-0.10.0.dist-info/METADATA
isodata-0.10.0.dist-info/WHEEL
isodata-0.10.0.dist-info/top_level.txt
isodata-0.10.0.dist-info/RECORD
