Metadata-Version: 2.1
Name: isodata
Version: 0.10.0
Summary: API to access energy data
Author-email: Max Kanter <kmax12@gmail.com>
Maintainer-email: Max Kanter <kmax12@gmail.com>
License: Copyright 2022 James Max Kanter        
Project-URL: Source Code, https://github.com/kmax12/isodata/
Project-URL: Changes, https://github.com/kmax12/isodata/blob/main/CHANGELOG.md
Project-URL: Issue Tracker, https://github.com/kmax12/isodata/issues
Keywords: energy,independent system operator
Classifier: Programming Language :: Python
Classifier: Programming Language :: Python :: 3
Classifier: Programming Language :: Python :: 3.7
Classifier: Programming Language :: Python :: 3.8
Classifier: Programming Language :: Python :: 3.9
Classifier: Programming Language :: Python :: 3.10
Requires-Python: <4,>=3.7
License-File: LICENSE
Requires-Dist: requests (>=2.28.1)
Requires-Dist: pandas (>=1.3.0)
Requires-Dist: beautifulsoup4 (>=4.8.13)
Requires-Dist: tabulate (>=0.8.10)
Requires-Dist: tqdm (>=4.64.1)
Provides-Extra: dev
Requires-Dist: flake8 (==5.0.4) ; extra == 'dev'
Requires-Dist: isort (==5.10.1) ; extra == 'dev'
Requires-Dist: black (==22.6.0) ; extra == 'dev'
Requires-Dist: pre-commit (==2.20.0) ; extra == 'dev'
Requires-Dist: isodata[dev] ; extra == 'dev'
Provides-Extra: test
Requires-Dist: pytest (==7.1.2) ; extra == 'test'
